{
 "actions": [],
 "allow_rename": 1,
 "creation": "2024-04-18 01:27:35.697937",
 "default_view": "List",
 "doctype": "DocType",
 "editable_grid": 1,
 "engine": "InnoDB",
 "field_order": [
  "start_time",
  "end_time"
 ],
 "fields": [
  {
   "fieldname": "start_time",
   "fieldtype": "Time",
   "in_list_view": 1,
   "label": "Start Time",
   "reqd": 1
  },
  {
   "fieldname": "end_time",
   "fieldtype": "Time",
   "in_list_view": 1,
   "label": "End Time",
   "reqd": 1
  }
 ],
 "index_web_pages_for_search": 1,
 "istable": 1,
 "links": [],
 "modified": "2024-04-18 01:28:24.855298",
 "modified_by": "Administrator",
 "module": "Appointment App",
 "name": "Doctor Shift",
 "owner": "Administrator",
 "permissions": [],
 "sort_field": "modified",
 "sort_order": "DESC",
 "states": [],
 "track_changes": 1,
 "track_seen": 1
}